{
  "title": "Design an API Gateway",
  "slug": "design-api-gateway",
  "difficulty": "Hard",
  "category": "system_design",
  "points": 200,
  "tags": ["API Gateway", "Microservices", "Routing", "Security"],
  "company_tags": ["Amazon", "Netflix", "Uber", "Lyft"],
  "topic_tags": ["Reverse Proxy", "Load Balancing", "Authentication", "Rate Limiting", "Request Transformation"],
  "time_limit_ms": 2000,
  "memory_limit_kb": 262144,
  "input_format": "Incoming HTTP requests with various paths, headers, and payloads",
  "output_format": "Routed requests to downstream services or error responses (4xx, 5xx)",
  "example_input": "GET /api/v1/orders HTTP/1.1\nHost: api.shop.com\nAuthorization: Bearer <token>",
  "example_output": "Forward to OrderService:8080/orders",
  "constraints": "1M+ RPS, Latency < 5ms, Circuit breaking, SSL termination.",
  "function_signature": "class ApiGateway {}",
  "status": "ACTIVE",
  "is_production_ready": true
}