{
  "title": "C++ Classes and Objects Quiz",
  "description": "Test your knowledge on blueprints, instances, and access specifiers.",
  "passingScore": 70,
  "questions": [
    {
      "question": "In OOP terms, if 'Class' is a blueprint for a house, what is the 'Object'?",
      "options": [
        "The architect's drawing",
        "The tools used to build it",
        "A specific, physical house built from that blueprint",
        "The neighborhood where it's located"
      ],
      "correctAnswer": 2,
      "points": 10
    }
  ]
}
